README.txt
setup.cfg
setup.py
BBCS_Tools.egg-info/PKG-INFO
BBCS_Tools.egg-info/SOURCES.txt
BBCS_Tools.egg-info/dependency_links.txt
BBCS_Tools.egg-info/entry_points.txt
BBCS_Tools.egg-info/requires.txt
BBCS_Tools.egg-info/top_level.txt
bbcs_tools/__init__.py
bbcs_tools/bitbucket.py
bbcs_tools/coveralls.py
bbcs_tools/pypi.py