Metadata-Version: 1.1
Name: BBCS-Tools
Version: 1.0.2.1
Summary: Bitbucket Codeship integration tools.
Home-page: https://bitbucket.org/hellwig/BBCS-Tools/
Author: Martin P. Hellwig
Author-email: martin.hellwig@gmail.com
License: BSD
Download-URL: https://bitbucket.org/hellwig/BBCS-Tools/get/0d863c554c3b4f01057b5da5b2e8ddcf45fb63c3.zip
Keywords: Coveralls,Codeship,BitBucket,PyPI
Platform: UNKNOWN
Classifier: Programming Language :: Python :: 3
